drinfeld_modular_forms/__init__.py
drinfeld_modular_forms/drinfeld_modules.py
drinfeld_modular_forms/element.py
drinfeld_modular_forms/expansions.py
drinfeld_modular_forms/goss_polynomials.py
drinfeld_modular_forms/ring.py
drinfeld_modular_forms-0.2.dist-info/LICENSE
drinfeld_modular_forms-0.2.dist-info/METADATA
drinfeld_modular_forms-0.2.dist-info/WHEEL
drinfeld_modular_forms-0.2.dist-info/top_level.txt
drinfeld_modular_forms-0.2.dist-info/RECORD
