Metadata-Version: 2.1
Name: drinfeld-modular-forms
Version: 0.2
Summary: SageMath implementation of Drinfeld modular forms
Home-page: https://github.com/DavidAyotte/drinfeld_modular_forms
Author: David Ayotte
Author-email: davidayotte94@outlook.com
Classifier: Topic :: Scientific/Engineering :: Mathematics
Classifier: Intended Audience :: Science/Research
Classifier: Programming Language :: Python
Classifier: Operating System :: OS Independent
Classifier: Development Status :: 3 - Alpha
Classifier: License :: OSI Approved :: GNU General Public License v3 or later (GPLv3+)
License-File: LICENSE
Provides-Extra: doc
Requires-Dist: sphinx >=2 ; extra == 'doc'
